{
  "id": 12,
  "slug": "zunaizah-L200239281",

  "profile": {
    "full_name": "Zunaizah Zulfikar",
    "nim": "L200239281",
    "prodi": "Teknik Informatika",
    "angkatan": "2023",
    "photo_url": "/src/assets/iza.JPG",
    "headline": "Mahasiswa Teknik Informatika UMS | Pengembang Web Fullstack & Analisis Data",
    "short_bio": "Mahasiswa aktif UMS semester 5 dengan minat pada pengembangan web fullstack, dan analisis data .",
    "location": "Sukoharjo, Jawa Tengah",
    "portfolio_url": "localhost:5173"
  },

  "skills": [
    {
      "id": 1,
      "name": "ReactJS",
      "category": "technical",
      "level": "beginner",
      "is_main": false,
      "icon_url": "https://cdn.jsdelivr.net/gh/devicons/devicon/icons/react/react-original.svg"
    },
    {
      "id": 2,
      "name": "Django REST Framework",
      "category": "technical",
      "level": "beginner",
      "is_main": false,
      "icon_url": "https://cdn.jsdelivr.net/gh/devicons/devicon/icons/django/django-plain.svg"
    },
    {
      "id": 3,
      "name": "Bootsraps CSS",
      "category": "technical",
      "level": "beginner",
      "is_main": false,
      "icon_url": "https://cdn.jsdelivr.net/gh/devicons/devicon/icons/bootstrap/bootstrap-plain.svg"
    },
    {
      "id": 4,
      "name": "PHP Teamwork",
      "category": "technical",
      "level": "default",
      "is_main": false,
      "icon_url": "https://cdn.jsdelivr.net/gh/devicons/devicon/icons/php/php-original.svg"
    },
    {
      "id": 5,
      "name": "Python",
      "category": "technical",
      "level": "default",
      "is_main": false,
      "icon_url": "https://cdn.jsdelivr.net/gh/devicons/devicon/icons/python/python-original.svg"
    },
    {
      "id": 6,
      "name": "MySQL", 
      "category": "data",
      "level": "default",
      "is_main": true, 
      "years_of_experience": 1,
      "icon_url": "https://cdn.jsdelivr.net/gh/devicons/devicon/icons/mysql/mysql-original.svg"
    }
  ],

  "experiences": [
    {
      "id": 101,
      "title": "Desain Aplikasi Alquran",
      "organization": "MTQ UMS 2025",
      "experience_type": "audition",
      "start_date": "2025-07-09",
      "is_current": false,
      "description": "Merancang Aplikasi Desain Alquran.",
      "technologies": ["Figma", "DB Desainer", "Diagram"]
    },
    {
      "id": 102,
      "title": "Member of Ikatan Mahasiswa Muhammadiyah",
      "organization": "Ikatan Mahasiswa Muhammadiyah UMS",
      "experience_type": "organization",
      "start_date": "2023-01-01",
      "end_date": "now",
      "is_current": true,
      "description": ""
    },
    {
      "id": 103,
      "title": "Web Inventaris Kota",
      "organization": "Project",
      "experience_type": "project",
      "start_date": "2025-06-01",
      "end_date": null,
      "is_current": true,
      "description": "Merancang web peminjaman inventaris kota",
      "technologies": ["Figma", "DB Desainer", "Diagram"]
    }
  ],

  "statistics": {
    "views_count": 17,
    "profile_complete_percent": 92
  }
}